mcp_server_tls/__init__.py
mcp_server_tls/config.py
mcp_server_tls/consts.py
mcp_server_tls/main.py
mcp_server_tls/reqeust.py
mcp_server_tls/server.py
mcp_server_tls/utils.py
mcp_server_tls/resources/__init__.py
mcp_server_tls/resources/log.py
mcp_server_tls/resources/project.py
mcp_server_tls/resources/text_analysis.py
mcp_server_tls/resources/topic.py
mcp_server_tls/tools/__init__.py
mcp_server_tls/tools/log.py
mcp_server_tls/tools/project.py
mcp_server_tls/tools/text_analysis.py
mcp_server_tls/tools/topic.py
tls_mcp_server-0.1.0.dist-info/METADATA
tls_mcp_server-0.1.0.dist-info/WHEEL
tls_mcp_server-0.1.0.dist-info/entry_points.txt
tls_mcp_server-0.1.0.dist-info/top_level.txt
tls_mcp_server-0.1.0.dist-info/RECORD
