Metadata-Version: 2.4
Name: tls-mcp-server
Version: 0.1.0
Summary: TLS MCP server project
Requires-Python: >=3.13
Requires-Dist: httpx>=0.28.1
Requires-Dist: mcp[cli]>=1.6.0
Requires-Dist: python-dotenv>=1.0.1
Requires-Dist: volcengine>=1.0.175
